LICENSE
README.md
setup.py
fpuna_stable_diffusion/__init__.py
fpuna_stable_diffusion/lab2.py
fpuna_stable_diffusion/utils.py
fpuna_stable_diffusion.egg-info/PKG-INFO
fpuna_stable_diffusion.egg-info/SOURCES.txt
fpuna_stable_diffusion.egg-info/dependency_links.txt
fpuna_stable_diffusion.egg-info/top_level.txt