Metadata-Version: 2.1
Name: fpuna-stable-diffusion
Version: 0.0.2
Summary: Librería de soporte para el curso de Stable Diffusion
Author: Mateo Fidabel
License-File: LICENSE
